setup.py
PrettyTimedelta.egg-info/PKG-INFO
PrettyTimedelta.egg-info/SOURCES.txt
PrettyTimedelta.egg-info/dependency_links.txt
PrettyTimedelta.egg-info/top_level.txt
prettytimedelta/__init__.py
prettytimedelta/core.py
prettytimedelta/polish.py