Metadata-Version: 1.0
Name: PrettyTimedelta
Version: 0.1dev
Summary: Turn timedeltas into pretty format.
Home-page: UNKNOWN
Author: Jakub Warmuz
Author-email: jakub.warmuz@gmail.com
License: UNKNOWN
Keywords: timedelta pretty format date
Platform: UNKNOWN
